{
  "web": [
    {
      "date": "2025-08-20",
      "version": "site rev. #137",
      "title": "主页加入终端风 Changelog 摘要卡片",
      "items": [
        "终端黑底卡片（对比度更强）",
        "与凤凰背景的保护层融合，保持整体气质"
      ]
    },
    {
      "date": "2025-08-05",
      "version": "site rev. #136",
      "title": "Substack 改名为 Healing Notes｜疗愈札记，并统一导航/关于页",
      "items": ["文章卡片统一日期/排版"]
    }
  ],
  "app": [
    {
      "date": "2025-08-20",
      "version": "v0.7.2",
      "title": "引擎解释优化 & 事件线提示更聚焦",
      "items": ["新增当下可执行建议", "修复时区边界提示漂移"]
    },
    {
      "date": "2025-08-12",
      "version": "v0.7.0",
      "title": "独立命理引擎 Alpha 内测",
      "items": ["更细时间/方位结构化输出", "解释语言统一为“温柔而清晰”"]
    }
  ]
}
